smartutils/__init__.py
smartutils/math_utils.py
smartutils/string_utils.py
smartutils_math_utlities-0.1.0.dist-info/licenses/LICENSE
smartutils_math_utlities-0.1.0.dist-info/METADATA
smartutils_math_utlities-0.1.0.dist-info/WHEEL
smartutils_math_utlities-0.1.0.dist-info/top_level.txt
smartutils_math_utlities-0.1.0.dist-info/RECORD
