Metadata-Version: 2.4
Name: smartutils_math_utlities
Version: 0.1.0
Summary: A simple utility library for string and math operations
Author: Muhammad Faizan
Author-email: your_email@example.com
Requires-Python: >=3.6
License-File: LICENSE
Dynamic: author
Dynamic: author-email
Dynamic: description
Dynamic: description-content-type
Dynamic: license-file
Dynamic: requires-python
Dynamic: summary
